<?xml version="1.0" encoding="UTF-8"?>
<objects serializationModel="Studio.02.00.00">
	<object class="Workspace" id="{e664da57-884c-4445-8359-bca0e50a2f48}">
		<relationship name="projectSettings">
			<destination>{0698703d-e5f3-4304-ab34-42f1f7c2c32c}</destination>
		</relationship>
		<relationship name="profilerSessionFolder">
			<destination>{0f74e1a1-a216-4ffe-a466-8951452445bd}</destination>
		</relationship>
	</object>
	<object class="ProjectSettings" id="{0698703d-e5f3-4304-ab34-42f1f7c2c32c}">
		<relationship name="activePlatform">
			<destination>{d4bc6984-ee65-4a63-9597-8fabc5644299}</destination>
		</relationship>
	</object>
</objects>
